pyPMF/PMF.py
pyPMF/__init__.py
pyPMF/utils.py
pyPMF-0.1.0.dist-info/METADATA
pyPMF-0.1.0.dist-info/WHEEL
pyPMF-0.1.0.dist-info/top_level.txt
pyPMF-0.1.0.dist-info/RECORD
