Metadata-Version: 2.1
Name: pyPMF
Version: 0.1.0
Summary: UNKNOWN
Home-page: https://github.com/weber-s/pyPMF
Author: Samuël Weber
Author-email: samuel.weber@univ-grenoble-alpes.fr
License: UNKNOWN
Project-URL: Documentation, https://webersa.gricad-pages.univ-grenoble-alpes.fr/py4pm/
Project-URL: Source, https://github.com/weber-s/pyPMF
Platform: UNKNOWN
Classifier: Development Status :: 4 - Beta
Classifier: Intended Audience :: Science/Research
Classifier: Topic :: Scientific/Engineering :: Atmospheric Science
Classifier: Programming Language :: Python :: 3
Requires-Python: >=3
Requires-Dist: pandas
Requires-Dist: xlrd (<2)
Requires-Dist: matplotlib
Requires-Dist: seaborn
